odoo/addons/sale_order_price_recalculation/README.rst
odoo/addons/sale_order_price_recalculation/__init__.py
odoo/addons/sale_order_price_recalculation/__manifest__.py
odoo/addons/sale_order_price_recalculation/i18n/ca.po
odoo/addons/sale_order_price_recalculation/i18n/de.po
odoo/addons/sale_order_price_recalculation/i18n/el_GR.po
odoo/addons/sale_order_price_recalculation/i18n/en.po
odoo/addons/sale_order_price_recalculation/i18n/es.po
odoo/addons/sale_order_price_recalculation/i18n/es_ES.po
odoo/addons/sale_order_price_recalculation/i18n/es_VE.po
odoo/addons/sale_order_price_recalculation/i18n/fi.po
odoo/addons/sale_order_price_recalculation/i18n/fr.po
odoo/addons/sale_order_price_recalculation/i18n/hr.po
odoo/addons/sale_order_price_recalculation/i18n/hr_HR.po
odoo/addons/sale_order_price_recalculation/i18n/hu.po
odoo/addons/sale_order_price_recalculation/i18n/it.po
odoo/addons/sale_order_price_recalculation/i18n/nl.po
odoo/addons/sale_order_price_recalculation/i18n/nl_NL.po
odoo/addons/sale_order_price_recalculation/i18n/pt.po
odoo/addons/sale_order_price_recalculation/i18n/pt_BR.po
odoo/addons/sale_order_price_recalculation/i18n/ro.po
odoo/addons/sale_order_price_recalculation/i18n/sale_order_price_recalculation.pot
odoo/addons/sale_order_price_recalculation/i18n/sl.po
odoo/addons/sale_order_price_recalculation/i18n/tr.po
odoo/addons/sale_order_price_recalculation/i18n/tr_TR.po
odoo/addons/sale_order_price_recalculation/i18n/vi_VN.po
odoo/addons/sale_order_price_recalculation/i18n/zh_CN.po
odoo/addons/sale_order_price_recalculation/models/__init__.py
odoo/addons/sale_order_price_recalculation/models/sale_order.py
odoo/addons/sale_order_price_recalculation/static/description/icon.png
odoo/addons/sale_order_price_recalculation/static/description/sale_order_price_recalculation.png
odoo/addons/sale_order_price_recalculation/tests/__init__.py
odoo/addons/sale_order_price_recalculation/tests/test_sale_order_price_recalculation.py
odoo11_addon_sale_order_price_recalculation-11.0.1.0.1.dist-info/METADATA
odoo11_addon_sale_order_price_recalculation-11.0.1.0.1.dist-info/WHEEL
odoo11_addon_sale_order_price_recalculation-11.0.1.0.1.dist-info/top_level.txt
odoo11_addon_sale_order_price_recalculation-11.0.1.0.1.dist-info/RECORD
